{
    "reason": "",
    "state": "MERGED",
    "updated_on": "2016-01-21T18:58:00.335583+00:00",
    "comment_count": 1,
    "description": "",
    "created_on": "2016-01-21T18:01:51.917900+00:00",
    "task_count": 0,
    "merge_commit": {
        "links": {
            "self": {
                "href": "https://api.bitbucket.org/2.0/repositories/yt_analysis/yt/commit/eff6841ae4004a3ecb8040858e57badbd3b00021"
            }
        },
        "hash": "eff6841ae4004a3ecb8040858e57badbd3b00021"
    },
    "title": "[bugfix/3.3] Add missing .add_subpackage for tqdm",
    "links": {
        "diff": {
            "href": "https://api.bitbucket.org/2.0/repositories/yt_analysis/yt/pullrequests/1951/diff"
        },
        "decline": {
            "href": "https://api.bitbucket.org/2.0/repositories/yt_analysis/yt/pullrequests/1951/decline"
        },
        "self": {
            "href": "https://api.bitbucket.org/2.0/repositories/yt_analysis/yt/pullrequests/1951"
        },
        "activity": {
            "href": "https://api.bitbucket.org/2.0/repositories/yt_analysis/yt/pullrequests/1951/activity"
        },
        "merge": {
            "href": "https://api.bitbucket.org/2.0/repositories/yt_analysis/yt/pullrequests/1951/merge"
        },
        "commits": {
            "href": "https://api.bitbucket.org/2.0/repositories/yt_analysis/yt/pullrequests/1951/commits"
        },
        "statuses": {
            "href": "https://api.bitbucket.org/2.0/repositories/yt_analysis/yt/pullrequests/1951/statuses"
        },
        "approve": {
            "href": "https://api.bitbucket.org/2.0/repositories/yt_analysis/yt/pullrequests/1951/approve"
        },
        "html": {
            "href": "https://bitbucket.org/yt_analysis/yt/pull-requests/1951"
        },
        "comments": {
            "href": "https://api.bitbucket.org/2.0/repositories/yt_analysis/yt/pullrequests/1951/comments"
        }
    },
    "closed_by": {
        "links": {
            "self": {
                "href": "https://api.bitbucket.org/2.0/users/ngoldbaum"
            },
            "html": {
                "href": "https://bitbucket.org/ngoldbaum/"
            },
            "avatar": {
                "href": "https://bitbucket.org/account/ngoldbaum/avatar/32/"
            }
        },
        "type": "user",
        "display_name": "Nathan Goldbaum",
        "uuid": "{5dcd72da-6420-4a6d-9571-e75dffcac587}",
        "username": "ngoldbaum"
    },
    "id": 1951,
    "type": "pullrequest",
    "author": {
        "links": {
            "self": {
                "href": "https://api.bitbucket.org/2.0/users/xarthisius"
            },
            "html": {
                "href": "https://bitbucket.org/xarthisius/"
            },
            "avatar": {
                "href": "https://bitbucket.org/account/xarthisius/avatar/32/"
            }
        },
        "type": "user",
        "display_name": "Kacper Kowalik",
        "uuid": "{26af8f1d-35b3-46ce-9939-09915b06e31f}",
        "username": "xarthisius"
    },
    "source": {
        "branch": {
            "name": "yt"
        },
        "commit": {
            "links": {
                "self": {
                    "href": "https://api.bitbucket.org/2.0/repositories/xarthisius/yt/commit/eff6841ae400"
                }
            },
            "hash": "eff6841ae400"
        },
        "repository": {
            "full_name": "xarthisius/yt",
            "type": "repository",
            "links": {
                "self": {
                    "href": "https://api.bitbucket.org/2.0/repositories/xarthisius/yt"
                },
                "html": {
                    "href": "https://bitbucket.org/xarthisius/yt"
                },
                "avatar": {
                    "href": "https://bitbucket.org/xarthisius/yt/avatar/32/"
                }
            },
            "name": "yt",
            "uuid": "{b753a527-1ccd-415c-8b85-3244947466a3}"
        }
    },
    "close_source_branch": false,
    "destination": {
        "branch": {
            "name": "yt"
        },
        "commit": {
            "links": {
                "self": {
                    "href": "https://api.bitbucket.org/2.0/repositories/yt_analysis/yt/commit/ce86a254c61e"
                }
            },
            "hash": "ce86a254c61e"
        },
        "repository": {
            "full_name": "yt_analysis/yt",
            "type": "repository",
            "links": {
                "self": {
                    "href": "https://api.bitbucket.org/2.0/repositories/yt_analysis/yt"
                },
                "html": {
                    "href": "https://bitbucket.org/yt_analysis/yt"
                },
                "avatar": {
                    "href": "https://bitbucket.org/yt_analysis/yt/avatar/32/"
                }
            },
            "name": "yt",
            "uuid": "{b73cb37c-40f2-493a-aaa9-41bc8d8974cc}"
        }
    },
    "comments": [
        {
            "user": {
                "links": {
                    "self": {
                        "href": "https://api.bitbucket.org/2.0/users/yt-fido"
                    },
                    "html": {
                        "href": "https://bitbucket.org/yt-fido/"
                    },
                    "avatar": {
                        "href": "https://bitbucket.org/account/yt-fido/avatar/32/"
                    }
                },
                "type": "user",
                "display_name": "yt-fido",
                "uuid": "{da2aa332-3f05-45c9-ae53-ff5ba34b35ce}",
                "username": "yt-fido"
            },
            "type": "pullrequest_comment",
            "links": {
                "self": {
                    "href": "https://api.bitbucket.org/2.0/repositories/yt_analysis/yt/pullrequests/1951/comments/13730955"
                },
                "html": {
                    "href": "https://bitbucket.org/yt_analysis/yt/pull-requests/1951/_/diff#comment-13730955"
                }
            },
            "pullrequest": {
                "title": "[bugfix/3.3] Add missing .add_subpackage for tqdm",
                "type": "pullrequest",
                "links": {
                    "self": {
                        "href": "https://api.bitbucket.org/2.0/repositories/yt_analysis/yt/pullrequests/1951"
                    },
                    "html": {
                        "href": "https://bitbucket.org/yt_analysis/yt/pull-requests/1951"
                    }
                },
                "id": 1951
            },
            "content": {
                "raw": "All tests pass. Good job!",
                "html": "<p>All tests pass. Good job!</p>",
                "markup": "markdown"
            },
            "created_on": "2016-01-21T18:57:16.590525+00:00",
            "updated_on": "2016-01-21T18:57:16.643615+00:00",
            "id": 13730955
        }
    ]
}