{
    "reason": "",
    "state": "MERGED",
    "updated_on": "2016-08-13T06:49:33.105979+00:00",
    "comment_count": 0,
    "description": "gravitational_potential was missing in athena frontend",
    "created_on": "2016-08-11T17:10:23.292610+00:00",
    "task_count": 0,
    "merge_commit": {
        "links": {
            "self": {
                "href": "https://api.bitbucket.org/2.0/repositories/yt_analysis/yt/commit/56c0b53b459c"
            }
        },
        "hash": "56c0b53b459c"
    },
    "title": "Add gravitational_potential to known_other_fields for athena frontend",
    "links": {
        "diff": {
            "href": "https://api.bitbucket.org/2.0/repositories/yt_analysis/yt/pullrequests/2333/diff"
        },
        "decline": {
            "href": "https://api.bitbucket.org/2.0/repositories/yt_analysis/yt/pullrequests/2333/decline"
        },
        "self": {
            "href": "https://api.bitbucket.org/2.0/repositories/yt_analysis/yt/pullrequests/2333"
        },
        "activity": {
            "href": "https://api.bitbucket.org/2.0/repositories/yt_analysis/yt/pullrequests/2333/activity"
        },
        "merge": {
            "href": "https://api.bitbucket.org/2.0/repositories/yt_analysis/yt/pullrequests/2333/merge"
        },
        "commits": {
            "href": "https://api.bitbucket.org/2.0/repositories/yt_analysis/yt/pullrequests/2333/commits"
        },
        "statuses": {
            "href": "https://api.bitbucket.org/2.0/repositories/yt_analysis/yt/pullrequests/2333/statuses"
        },
        "approve": {
            "href": "https://api.bitbucket.org/2.0/repositories/yt_analysis/yt/pullrequests/2333/approve"
        },
        "html": {
            "href": "https://bitbucket.org/yt_analysis/yt/pull-requests/2333"
        },
        "comments": {
            "href": "https://api.bitbucket.org/2.0/repositories/yt_analysis/yt/pullrequests/2333/comments"
        }
    },
    "closed_by": {
        "links": {
            "self": {
                "href": "https://api.bitbucket.org/2.0/users/ngoldbaum"
            },
            "html": {
                "href": "https://bitbucket.org/ngoldbaum/"
            },
            "avatar": {
                "href": "https://bitbucket.org/account/ngoldbaum/avatar/32/"
            }
        },
        "type": "user",
        "display_name": "Nathan Goldbaum",
        "uuid": "{5dcd72da-6420-4a6d-9571-e75dffcac587}",
        "username": "ngoldbaum"
    },
    "id": 2333,
    "type": "pullrequest",
    "author": {
        "links": {
            "self": {
                "href": "https://api.bitbucket.org/2.0/users/changgoo"
            },
            "html": {
                "href": "https://bitbucket.org/changgoo/"
            },
            "avatar": {
                "href": "https://bitbucket.org/account/changgoo/avatar/32/"
            }
        },
        "type": "user",
        "display_name": "Chang-Goo Kim",
        "uuid": "{e1c8d14c-75f7-4d22-99c5-33a702415b24}",
        "username": "changgoo"
    },
    "source": {
        "branch": {
            "name": "yt"
        },
        "commit": {
            "links": {
                "self": {
                    "href": "https://api.bitbucket.org/2.0/repositories/changgoo/yt/commit/476b51e9d1c1"
                }
            },
            "hash": "476b51e9d1c1"
        },
        "repository": {
            "full_name": "changgoo/yt",
            "type": "repository",
            "links": {
                "self": {
                    "href": "https://api.bitbucket.org/2.0/repositories/changgoo/yt"
                },
                "html": {
                    "href": "https://bitbucket.org/changgoo/yt"
                },
                "avatar": {
                    "href": "https://bitbucket.org/changgoo/yt/avatar/32/"
                }
            },
            "name": "yt",
            "uuid": "{41ee3882-f9fe-4858-9c56-cf61d4f3a820}"
        }
    },
    "close_source_branch": false,
    "destination": {
        "branch": {
            "name": "yt"
        },
        "commit": {
            "links": {
                "self": {
                    "href": "https://api.bitbucket.org/2.0/repositories/yt_analysis/yt/commit/844f5912f3bb"
                }
            },
            "hash": "844f5912f3bb"
        },
        "repository": {
            "full_name": "yt_analysis/yt",
            "type": "repository",
            "links": {
                "self": {
                    "href": "https://api.bitbucket.org/2.0/repositories/yt_analysis/yt"
                },
                "html": {
                    "href": "https://bitbucket.org/yt_analysis/yt"
                },
                "avatar": {
                    "href": "https://bitbucket.org/yt_analysis/yt/avatar/32/"
                }
            },
            "name": "yt",
            "uuid": "{b73cb37c-40f2-493a-aaa9-41bc8d8974cc}"
        }
    },
    "comments": []
}