{
    "reason": "",
    "state": "MERGED",
    "updated_on": "2016-03-23T20:49:45.869503+00:00",
    "comment_count": 5,
    "description": "",
    "created_on": "2016-03-17T02:41:50.982396+00:00",
    "task_count": 0,
    "merge_commit": {
        "links": {
            "self": {
                "href": "https://api.bitbucket.org/2.0/repositories/yt_analysis/yt/commit/a58aff2c0219"
            }
        },
        "hash": "a58aff2c0219"
    },
    "title": "Include supported version numbers in setup classifiers",
    "links": {
        "diff": {
            "href": "https://api.bitbucket.org/2.0/repositories/yt_analysis/yt/pullrequests/2048/diff"
        },
        "decline": {
            "href": "https://api.bitbucket.org/2.0/repositories/yt_analysis/yt/pullrequests/2048/decline"
        },
        "self": {
            "href": "https://api.bitbucket.org/2.0/repositories/yt_analysis/yt/pullrequests/2048"
        },
        "activity": {
            "href": "https://api.bitbucket.org/2.0/repositories/yt_analysis/yt/pullrequests/2048/activity"
        },
        "merge": {
            "href": "https://api.bitbucket.org/2.0/repositories/yt_analysis/yt/pullrequests/2048/merge"
        },
        "commits": {
            "href": "https://api.bitbucket.org/2.0/repositories/yt_analysis/yt/pullrequests/2048/commits"
        },
        "statuses": {
            "href": "https://api.bitbucket.org/2.0/repositories/yt_analysis/yt/pullrequests/2048/statuses"
        },
        "approve": {
            "href": "https://api.bitbucket.org/2.0/repositories/yt_analysis/yt/pullrequests/2048/approve"
        },
        "html": {
            "href": "https://bitbucket.org/yt_analysis/yt/pull-requests/2048"
        },
        "comments": {
            "href": "https://api.bitbucket.org/2.0/repositories/yt_analysis/yt/pullrequests/2048/comments"
        }
    },
    "closed_by": {
        "links": {
            "self": {
                "href": "https://api.bitbucket.org/2.0/users/ngoldbaum"
            },
            "html": {
                "href": "https://bitbucket.org/ngoldbaum/"
            },
            "avatar": {
                "href": "https://bitbucket.org/account/ngoldbaum/avatar/32/"
            }
        },
        "type": "user",
        "display_name": "Nathan Goldbaum",
        "uuid": "{5dcd72da-6420-4a6d-9571-e75dffcac587}",
        "username": "ngoldbaum"
    },
    "id": 2048,
    "type": "pullrequest",
    "author": {
        "links": {
            "self": {
                "href": "https://api.bitbucket.org/2.0/users/migueldvb"
            },
            "html": {
                "href": "https://bitbucket.org/migueldvb/"
            },
            "avatar": {
                "href": "https://bitbucket.org/account/migueldvb/avatar/32/"
            }
        },
        "type": "user",
        "display_name": "Miguel de Val-Borro",
        "uuid": "{f05213b9-ea8e-469c-b0ff-2d72274c22fe}",
        "username": "migueldvb"
    },
    "source": {
        "branch": {
            "name": "yt"
        },
        "commit": {
            "links": {
                "self": {
                    "href": "https://api.bitbucket.org/2.0/repositories/migueldvb/yt/commit/063ec7f053eb"
                }
            },
            "hash": "063ec7f053eb"
        },
        "repository": {
            "full_name": "migueldvb/yt",
            "type": "repository",
            "links": {
                "self": {
                    "href": "https://api.bitbucket.org/2.0/repositories/migueldvb/yt"
                },
                "html": {
                    "href": "https://bitbucket.org/migueldvb/yt"
                },
                "avatar": {
                    "href": "https://bitbucket.org/migueldvb/yt/avatar/32/"
                }
            },
            "name": "yt",
            "uuid": "{81515406-9db6-4820-8452-f61e1ff2ae38}"
        }
    },
    "close_source_branch": false,
    "destination": {
        "branch": {
            "name": "yt"
        },
        "commit": {
            "links": {
                "self": {
                    "href": "https://api.bitbucket.org/2.0/repositories/yt_analysis/yt/commit/293bfec508a7"
                }
            },
            "hash": "293bfec508a7"
        },
        "repository": {
            "full_name": "yt_analysis/yt",
            "type": "repository",
            "links": {
                "self": {
                    "href": "https://api.bitbucket.org/2.0/repositories/yt_analysis/yt"
                },
                "html": {
                    "href": "https://bitbucket.org/yt_analysis/yt"
                },
                "avatar": {
                    "href": "https://bitbucket.org/yt_analysis/yt/avatar/32/"
                }
            },
            "name": "yt",
            "uuid": "{b73cb37c-40f2-493a-aaa9-41bc8d8974cc}"
        }
    },
    "comments": [
        {
            "user": {
                "links": {
                    "self": {
                        "href": "https://api.bitbucket.org/2.0/users/yt-fido"
                    },
                    "html": {
                        "href": "https://bitbucket.org/yt-fido/"
                    },
                    "avatar": {
                        "href": "https://bitbucket.org/account/yt-fido/avatar/32/"
                    }
                },
                "type": "user",
                "display_name": "yt-fido",
                "uuid": "{da2aa332-3f05-45c9-ae53-ff5ba34b35ce}",
                "username": "yt-fido"
            },
            "type": "pullrequest_comment",
            "links": {
                "self": {
                    "href": "https://api.bitbucket.org/2.0/repositories/yt_analysis/yt/pullrequests/2048/comments/15875947"
                },
                "html": {
                    "href": "https://bitbucket.org/yt_analysis/yt/pull-requests/2048/_/diff#comment-15875947"
                }
            },
            "pullrequest": {
                "title": "Include supported version numbers in setup classifiers",
                "type": "pullrequest",
                "links": {
                    "self": {
                        "href": "https://api.bitbucket.org/2.0/repositories/yt_analysis/yt/pullrequests/2048"
                    },
                    "html": {
                        "href": "https://bitbucket.org/yt_analysis/yt/pull-requests/2048"
                    }
                },
                "id": 2048
            },
            "content": {
                "raw": "All tests pass. Good job! https://tests.yt-project.org/job/yt_testsuite/111/",
                "html": "<p>All tests pass. Good job! <a href=\"https://tests.yt-project.org/job/yt_testsuite/111/\" rel=\"nofollow\">https://tests.yt-project.org/job/yt_testsuite/111/</a></p>",
                "markup": "markdown"
            },
            "created_on": "2016-03-17T04:03:00.118899+00:00",
            "updated_on": "2016-03-17T04:03:00.525865+00:00",
            "id": 15875947
        },
        {
            "user": {
                "links": {
                    "self": {
                        "href": "https://api.bitbucket.org/2.0/users/MatthewTurk"
                    },
                    "html": {
                        "href": "https://bitbucket.org/MatthewTurk/"
                    },
                    "avatar": {
                        "href": "https://bitbucket.org/account/MatthewTurk/avatar/32/"
                    }
                },
                "type": "user",
                "display_name": "Matthew Turk",
                "uuid": "{b3f0b280-55fc-4e8a-8bd1-40478d4cbdbf}",
                "username": "MatthewTurk"
            },
            "type": "pullrequest_comment",
            "links": {
                "self": {
                    "href": "https://api.bitbucket.org/2.0/repositories/yt_analysis/yt/pullrequests/2048/comments/15971120"
                },
                "html": {
                    "href": "https://bitbucket.org/yt_analysis/yt/pull-requests/2048/_/diff#comment-15971120"
                }
            },
            "pullrequest": {
                "title": "Include supported version numbers in setup classifiers",
                "type": "pullrequest",
                "links": {
                    "self": {
                        "href": "https://api.bitbucket.org/2.0/repositories/yt_analysis/yt/pullrequests/2048"
                    },
                    "html": {
                        "href": "https://bitbucket.org/yt_analysis/yt/pull-requests/2048"
                    }
                },
                "id": 2048
            },
            "content": {
                "raw": "Should we also identify that we need 3.4 and above?",
                "html": "<p>Should we also identify that we need 3.4 and above?</p>",
                "markup": "markdown"
            },
            "created_on": "2016-03-18T17:56:11.318630+00:00",
            "updated_on": "2016-03-18T17:56:11.321484+00:00",
            "id": 15971120
        },
        {
            "user": {
                "links": {
                    "self": {
                        "href": "https://api.bitbucket.org/2.0/users/migueldvb"
                    },
                    "html": {
                        "href": "https://bitbucket.org/migueldvb/"
                    },
                    "avatar": {
                        "href": "https://bitbucket.org/account/migueldvb/avatar/32/"
                    }
                },
                "type": "user",
                "display_name": "Miguel de Val-Borro",
                "uuid": "{f05213b9-ea8e-469c-b0ff-2d72274c22fe}",
                "username": "migueldvb"
            },
            "type": "pullrequest_comment",
            "links": {
                "self": {
                    "href": "https://api.bitbucket.org/2.0/repositories/yt_analysis/yt/pullrequests/2048/comments/15971149"
                },
                "html": {
                    "href": "https://bitbucket.org/yt_analysis/yt/pull-requests/2048/_/diff#comment-15971149"
                }
            },
            "pullrequest": {
                "title": "Include supported version numbers in setup classifiers",
                "type": "pullrequest",
                "links": {
                    "self": {
                        "href": "https://api.bitbucket.org/2.0/repositories/yt_analysis/yt/pullrequests/2048"
                    },
                    "html": {
                        "href": "https://bitbucket.org/yt_analysis/yt/pull-requests/2048"
                    }
                },
                "id": 2048
            },
            "content": {
                "raw": "That's right, it should be included.",
                "html": "<p>That's right, it should be included.</p>",
                "markup": "markdown"
            },
            "created_on": "2016-03-18T17:57:03.667286+00:00",
            "updated_on": "2016-03-18T17:57:03.721108+00:00",
            "id": 15971149
        },
        {
            "user": {
                "links": {
                    "self": {
                        "href": "https://api.bitbucket.org/2.0/users/migueldvb"
                    },
                    "html": {
                        "href": "https://bitbucket.org/migueldvb/"
                    },
                    "avatar": {
                        "href": "https://bitbucket.org/account/migueldvb/avatar/32/"
                    }
                },
                "type": "user",
                "display_name": "Miguel de Val-Borro",
                "uuid": "{f05213b9-ea8e-469c-b0ff-2d72274c22fe}",
                "username": "migueldvb"
            },
            "type": "pullrequest_comment",
            "links": {
                "self": {
                    "href": "https://api.bitbucket.org/2.0/repositories/yt_analysis/yt/pullrequests/2048/comments/15971862"
                },
                "html": {
                    "href": "https://bitbucket.org/yt_analysis/yt/pull-requests/2048/_/diff#comment-15971862"
                }
            },
            "pullrequest": {
                "title": "Include supported version numbers in setup classifiers",
                "type": "pullrequest",
                "links": {
                    "self": {
                        "href": "https://api.bitbucket.org/2.0/repositories/yt_analysis/yt/pullrequests/2048"
                    },
                    "html": {
                        "href": "https://bitbucket.org/yt_analysis/yt/pull-requests/2048"
                    }
                },
                "id": 2048
            },
            "content": {
                "raw": "I think the classifiers should like this (including all supported versions) according to http://python-packaging-user-guide.readthedocs.org/en/latest/distributing/",
                "html": "<p>I think the classifiers should like this (including all supported versions) according to <a href=\"http://python-packaging-user-guide.readthedocs.org/en/latest/distributing/\" rel=\"nofollow\">http://python-packaging-user-guide.readthedocs.org/en/latest/distributing/</a></p>",
                "markup": "markdown"
            },
            "created_on": "2016-03-18T18:12:47.091257+00:00",
            "updated_on": "2016-03-18T18:12:47.395971+00:00",
            "id": 15971862
        },
        {
            "user": {
                "links": {
                    "self": {
                        "href": "https://api.bitbucket.org/2.0/users/yt-fido"
                    },
                    "html": {
                        "href": "https://bitbucket.org/yt-fido/"
                    },
                    "avatar": {
                        "href": "https://bitbucket.org/account/yt-fido/avatar/32/"
                    }
                },
                "type": "user",
                "display_name": "yt-fido",
                "uuid": "{da2aa332-3f05-45c9-ae53-ff5ba34b35ce}",
                "username": "yt-fido"
            },
            "type": "pullrequest_comment",
            "links": {
                "self": {
                    "href": "https://api.bitbucket.org/2.0/repositories/yt_analysis/yt/pullrequests/2048/comments/15973749"
                },
                "html": {
                    "href": "https://bitbucket.org/yt_analysis/yt/pull-requests/2048/_/diff#comment-15973749"
                }
            },
            "pullrequest": {
                "title": "Include supported version numbers in setup classifiers",
                "type": "pullrequest",
                "links": {
                    "self": {
                        "href": "https://api.bitbucket.org/2.0/repositories/yt_analysis/yt/pullrequests/2048"
                    },
                    "html": {
                        "href": "https://bitbucket.org/yt_analysis/yt/pull-requests/2048"
                    }
                },
                "id": 2048
            },
            "content": {
                "raw": "All tests pass. Good job! https://tests.yt-project.org/job/yt_testsuite/116/",
                "html": "<p>All tests pass. Good job! <a href=\"https://tests.yt-project.org/job/yt_testsuite/116/\" rel=\"nofollow\">https://tests.yt-project.org/job/yt_testsuite/116/</a></p>",
                "markup": "markdown"
            },
            "created_on": "2016-03-18T18:55:03.358618+00:00",
            "updated_on": "2016-03-18T18:55:03.438268+00:00",
            "id": 15973749
        }
    ]
}