{
    "reason": "",
    "state": "MERGED",
    "updated_on": "2016-10-17T21:20:32.964455+00:00",
    "comment_count": 6,
    "description": "Expand `~` and environment variables in the config file parameters, so we can do\r\n```\r\n[yt]\r\ntest_data_dir = ~/yt-data\r\n```\r\nor\r\n```\r\n[yt]\r\ntest_data_dir = $HOME/yt-data\r\n```",
    "created_on": "2016-10-10T23:22:28.250270+00:00",
    "task_count": 0,
    "merge_commit": {
        "links": {
            "self": {
                "href": "https://api.bitbucket.org/2.0/repositories/yt_analysis/yt/commit/2e22db274f5d"
            }
        },
        "hash": "2e22db274f5d"
    },
    "title": "Expand `~` and environment variables in the config file parameters",
    "links": {
        "diff": {
            "href": "https://api.bitbucket.org/2.0/repositories/yt_analysis/yt/pullrequests/2415/diff"
        },
        "decline": {
            "href": "https://api.bitbucket.org/2.0/repositories/yt_analysis/yt/pullrequests/2415/decline"
        },
        "self": {
            "href": "https://api.bitbucket.org/2.0/repositories/yt_analysis/yt/pullrequests/2415"
        },
        "activity": {
            "href": "https://api.bitbucket.org/2.0/repositories/yt_analysis/yt/pullrequests/2415/activity"
        },
        "merge": {
            "href": "https://api.bitbucket.org/2.0/repositories/yt_analysis/yt/pullrequests/2415/merge"
        },
        "commits": {
            "href": "https://api.bitbucket.org/2.0/repositories/yt_analysis/yt/pullrequests/2415/commits"
        },
        "statuses": {
            "href": "https://api.bitbucket.org/2.0/repositories/yt_analysis/yt/pullrequests/2415/statuses"
        },
        "approve": {
            "href": "https://api.bitbucket.org/2.0/repositories/yt_analysis/yt/pullrequests/2415/approve"
        },
        "html": {
            "href": "https://bitbucket.org/yt_analysis/yt/pull-requests/2415"
        },
        "comments": {
            "href": "https://api.bitbucket.org/2.0/repositories/yt_analysis/yt/pullrequests/2415/comments"
        }
    },
    "closed_by": {
        "links": {
            "self": {
                "href": "https://api.bitbucket.org/2.0/users/ngoldbaum"
            },
            "html": {
                "href": "https://bitbucket.org/ngoldbaum/"
            },
            "avatar": {
                "href": "https://bitbucket.org/account/ngoldbaum/avatar/32/"
            }
        },
        "type": "user",
        "display_name": "Nathan Goldbaum",
        "uuid": "{5dcd72da-6420-4a6d-9571-e75dffcac587}",
        "username": "ngoldbaum"
    },
    "id": 2415,
    "type": "pullrequest",
    "author": {
        "links": {
            "self": {
                "href": "https://api.bitbucket.org/2.0/users/qobilidop"
            },
            "html": {
                "href": "https://bitbucket.org/qobilidop/"
            },
            "avatar": {
                "href": "https://bitbucket.org/account/qobilidop/avatar/32/"
            }
        },
        "type": "user",
        "display_name": "Bili Dong",
        "uuid": "{3b9943d1-f045-4354-af1c-35efa961d7cd}",
        "username": "qobilidop"
    },
    "source": {
        "branch": {
            "name": "yt"
        },
        "commit": {
            "links": {
                "self": {
                    "href": "https://api.bitbucket.org/2.0/repositories/qobilidop/yt/commit/37c84abaa3f0"
                }
            },
            "hash": "37c84abaa3f0"
        },
        "repository": {
            "full_name": "qobilidop/yt",
            "type": "repository",
            "links": {
                "self": {
                    "href": "https://api.bitbucket.org/2.0/repositories/qobilidop/yt"
                },
                "html": {
                    "href": "https://bitbucket.org/qobilidop/yt"
                },
                "avatar": {
                    "href": "https://bitbucket.org/qobilidop/yt/avatar/32/"
                }
            },
            "name": "yt",
            "uuid": "{d9c776ae-b43e-4866-bdfd-e86c6031ba81}"
        }
    },
    "close_source_branch": false,
    "destination": {
        "branch": {
            "name": "yt"
        },
        "commit": {
            "links": {
                "self": {
                    "href": "https://api.bitbucket.org/2.0/repositories/yt_analysis/yt/commit/362ac1f1f4b6"
                }
            },
            "hash": "362ac1f1f4b6"
        },
        "repository": {
            "full_name": "yt_analysis/yt",
            "type": "repository",
            "links": {
                "self": {
                    "href": "https://api.bitbucket.org/2.0/repositories/yt_analysis/yt"
                },
                "html": {
                    "href": "https://bitbucket.org/yt_analysis/yt"
                },
                "avatar": {
                    "href": "https://bitbucket.org/yt_analysis/yt/avatar/32/"
                }
            },
            "name": "yt",
            "uuid": "{b73cb37c-40f2-493a-aaa9-41bc8d8974cc}"
        }
    },
    "comments": [
        {
            "user": {
                "links": {
                    "self": {
                        "href": "https://api.bitbucket.org/2.0/users/qobilidop"
                    },
                    "html": {
                        "href": "https://bitbucket.org/qobilidop/"
                    },
                    "avatar": {
                        "href": "https://bitbucket.org/account/qobilidop/avatar/32/"
                    }
                },
                "type": "user",
                "display_name": "Bili Dong",
                "uuid": "{3b9943d1-f045-4354-af1c-35efa961d7cd}",
                "username": "qobilidop"
            },
            "type": "pullrequest_comment",
            "links": {
                "self": {
                    "href": "https://api.bitbucket.org/2.0/repositories/yt_analysis/yt/pullrequests/2415/comments/24975731"
                },
                "html": {
                    "href": "https://bitbucket.org/yt_analysis/yt/pull-requests/2415/_/diff#comment-24975731"
                }
            },
            "pullrequest": {
                "title": "Expand `~` and environment variables in the config file parameters",
                "type": "pullrequest",
                "links": {
                    "self": {
                        "href": "https://api.bitbucket.org/2.0/repositories/yt_analysis/yt/pullrequests/2415"
                    },
                    "html": {
                        "href": "https://bitbucket.org/yt_analysis/yt/pull-requests/2415"
                    }
                },
                "id": 2415
            },
            "content": {
                "raw": "I've googled how to do this for `ConfigParser` generally, but haven't found a perfect satisfactory solution. An alternative way to achieve this is to also parse `os.environ` to `ytcfg` by `ytcfg.read_dict({\"yt\", os.environ})` for example. Then in the config file, the [\"interpolation\"](https://docs.python.org/3/library/configparser.html#interpolation-of-values) grammar could be used to parse `$HOME` as `%(HOME)s`. But there is potential danger that some parameter might be overrode by the environment variable. This could be solved by parsing `os.environ` first, followed by `ytcfg_defaults`.\n\nI kind of like being able to use `~` and `$HOME`, so I first implement it this way. But the `os.environ` method is also good. I cannot decide this by myself. Any suggestions or comments are welcomed!",
                "html": "<p>I've googled how to do this for <code>ConfigParser</code> generally, but haven't found a perfect satisfactory solution. An alternative way to achieve this is to also parse <code>os.environ</code> to <code>ytcfg</code> by <code>ytcfg.read_dict({\"yt\", os.environ})</code> for example. Then in the config file, the <a href=\"https://docs.python.org/3/library/configparser.html#interpolation-of-values\">\"interpolation\"</a> grammar could be used to parse <code>$HOME</code> as <code>%(HOME)s</code>. But there is potential danger that some parameter might be overrode by the environment variable. This could be solved by parsing <code>os.environ</code> first, followed by <code>ytcfg_defaults</code>.</p>\n<p>I kind of like being able to use <code>~</code> and <code>$HOME</code>, so I first implement it this way. But the <code>os.environ</code> method is also good. I cannot decide this by myself. Any suggestions or comments are welcomed!</p>",
                "markup": "markdown"
            },
            "created_on": "2016-10-10T23:27:30.012339+00:00",
            "updated_on": "2016-10-10T23:27:30.017377+00:00",
            "id": 24975731
        },
        {
            "user": {
                "links": {
                    "self": {
                        "href": "https://api.bitbucket.org/2.0/users/ngoldbaum"
                    },
                    "html": {
                        "href": "https://bitbucket.org/ngoldbaum/"
                    },
                    "avatar": {
                        "href": "https://bitbucket.org/account/ngoldbaum/avatar/32/"
                    }
                },
                "type": "user",
                "display_name": "Nathan Goldbaum",
                "uuid": "{5dcd72da-6420-4a6d-9571-e75dffcac587}",
                "username": "ngoldbaum"
            },
            "type": "pullrequest_comment",
            "links": {
                "self": {
                    "href": "https://api.bitbucket.org/2.0/repositories/yt_analysis/yt/pullrequests/2415/comments/24976096"
                },
                "html": {
                    "href": "https://bitbucket.org/yt_analysis/yt/pull-requests/2415/_/diff#comment-24976096"
                }
            },
            "pullrequest": {
                "title": "Expand `~` and environment variables in the config file parameters",
                "type": "pullrequest",
                "links": {
                    "self": {
                        "href": "https://api.bitbucket.org/2.0/repositories/yt_analysis/yt/pullrequests/2415"
                    },
                    "html": {
                        "href": "https://bitbucket.org/yt_analysis/yt/pull-requests/2415"
                    }
                },
                "id": 2415
            },
            "content": {
                "raw": "Sorry, can you clarify a bit more what this changes? Does this make it so I can do things like:\n\n```\n[yt]\ntest_data_dir = ~/Documents/test\n```\n\nIf so, awesome!\n\nWouldn't hurt to add some tests to `yt/utilities/tests/test_config.py`.",
                "html": "<p>Sorry, can you clarify a bit more what this changes? Does this make it so I can do things like:</p>\n<div class=\"codehilite\"><pre><span></span><span class=\"k\">[yt]</span>\n<span class=\"na\">test_data_dir</span> <span class=\"o\">=</span> <span class=\"s\">~/Documents/test</span>\n</pre></div>\n\n\n<p>If so, awesome!</p>\n<p>Wouldn't hurt to add some tests to <code>yt/utilities/tests/test_config.py</code>.</p>",
                "markup": "markdown"
            },
            "created_on": "2016-10-10T23:42:51.274919+00:00",
            "updated_on": "2016-10-10T23:42:51.282714+00:00",
            "id": 24976096
        },
        {
            "user": {
                "links": {
                    "self": {
                        "href": "https://api.bitbucket.org/2.0/users/qobilidop"
                    },
                    "html": {
                        "href": "https://bitbucket.org/qobilidop/"
                    },
                    "avatar": {
                        "href": "https://bitbucket.org/account/qobilidop/avatar/32/"
                    }
                },
                "type": "user",
                "display_name": "Bili Dong",
                "uuid": "{3b9943d1-f045-4354-af1c-35efa961d7cd}",
                "username": "qobilidop"
            },
            "type": "pullrequest_comment",
            "links": {
                "self": {
                    "href": "https://api.bitbucket.org/2.0/repositories/yt_analysis/yt/pullrequests/2415/comments/24976119"
                },
                "html": {
                    "href": "https://bitbucket.org/yt_analysis/yt/pull-requests/2415/_/diff#comment-24976119"
                }
            },
            "parent": {
                "links": {
                    "self": {
                        "href": "https://api.bitbucket.org/2.0/repositories/yt_analysis/yt/pullrequests/2415/comments/24976096"
                    },
                    "html": {
                        "href": "https://bitbucket.org/yt_analysis/yt/pull-requests/2415/_/diff#comment-24976096"
                    }
                },
                "id": 24976096
            },
            "pullrequest": {
                "title": "Expand `~` and environment variables in the config file parameters",
                "type": "pullrequest",
                "links": {
                    "self": {
                        "href": "https://api.bitbucket.org/2.0/repositories/yt_analysis/yt/pullrequests/2415"
                    },
                    "html": {
                        "href": "https://bitbucket.org/yt_analysis/yt/pull-requests/2415"
                    }
                },
                "id": 2415
            },
            "content": {
                "raw": "Yes, that's what I meant to implement. Sure I'll add the test.",
                "html": "<p>Yes, that's what I meant to implement. Sure I'll add the test.</p>",
                "markup": "markdown"
            },
            "created_on": "2016-10-10T23:44:00.888048+00:00",
            "updated_on": "2016-10-10T23:44:00.890608+00:00",
            "id": 24976119
        },
        {
            "user": {
                "links": {
                    "self": {
                        "href": "https://api.bitbucket.org/2.0/users/yt-fido"
                    },
                    "html": {
                        "href": "https://bitbucket.org/yt-fido/"
                    },
                    "avatar": {
                        "href": "https://bitbucket.org/account/yt-fido/avatar/32/"
                    }
                },
                "type": "user",
                "display_name": "yt-fido",
                "uuid": "{da2aa332-3f05-45c9-ae53-ff5ba34b35ce}",
                "username": "yt-fido"
            },
            "type": "pullrequest_comment",
            "links": {
                "self": {
                    "href": "https://api.bitbucket.org/2.0/repositories/yt_analysis/yt/pullrequests/2415/comments/24976717"
                },
                "html": {
                    "href": "https://bitbucket.org/yt_analysis/yt/pull-requests/2415/_/diff#comment-24976717"
                }
            },
            "pullrequest": {
                "title": "Expand `~` and environment variables in the config file parameters",
                "type": "pullrequest",
                "links": {
                    "self": {
                        "href": "https://api.bitbucket.org/2.0/repositories/yt_analysis/yt/pullrequests/2415"
                    },
                    "html": {
                        "href": "https://bitbucket.org/yt_analysis/yt/pull-requests/2415"
                    }
                },
                "id": 2415
            },
            "content": {
                "raw": "* All tests pass. Good job! https://tests.yt-project.org/job/yt_testsuite/300/\n* Something went wrong, you should checkout https://tests.yt-project.org/job/yt_testsuite/303/\n* Something went wrong, you should checkout https://tests.yt-project.org/job/yt_testsuite/304/\n* All tests pass. Good job! https://tests.yt-project.org/job/yt_testsuite/306/\n",
                "html": "<ul>\n<li>All tests pass. Good job! <a href=\"https://tests.yt-project.org/job/yt_testsuite/300/\" rel=\"nofollow\">https://tests.yt-project.org/job/yt_testsuite/300/</a></li>\n<li>Something went wrong, you should checkout <a href=\"https://tests.yt-project.org/job/yt_testsuite/303/\" rel=\"nofollow\">https://tests.yt-project.org/job/yt_testsuite/303/</a></li>\n<li>Something went wrong, you should checkout <a href=\"https://tests.yt-project.org/job/yt_testsuite/304/\" rel=\"nofollow\">https://tests.yt-project.org/job/yt_testsuite/304/</a></li>\n<li>All tests pass. Good job! <a href=\"https://tests.yt-project.org/job/yt_testsuite/306/\" rel=\"nofollow\">https://tests.yt-project.org/job/yt_testsuite/306/</a></li>\n</ul>",
                "markup": "markdown"
            },
            "created_on": "2016-10-11T00:10:51.595190+00:00",
            "updated_on": "2016-10-11T06:38:23.863173+00:00",
            "id": 24976717
        },
        {
            "user": {
                "links": {
                    "self": {
                        "href": "https://api.bitbucket.org/2.0/users/qobilidop"
                    },
                    "html": {
                        "href": "https://bitbucket.org/qobilidop/"
                    },
                    "avatar": {
                        "href": "https://bitbucket.org/account/qobilidop/avatar/32/"
                    }
                },
                "type": "user",
                "display_name": "Bili Dong",
                "uuid": "{3b9943d1-f045-4354-af1c-35efa961d7cd}",
                "username": "qobilidop"
            },
            "type": "pullrequest_comment",
            "links": {
                "self": {
                    "href": "https://api.bitbucket.org/2.0/repositories/yt_analysis/yt/pullrequests/2415/comments/24979863"
                },
                "code": {
                    "href": "https://api.bitbucket.org/2.0/repositories/yt_analysis/yt/diff/qobilidop/yt:37c84abaa3f0..362ac1f1f4b6?path=yt%2Futilities%2Ftests%2Ftest_config.py"
                },
                "html": {
                    "href": "https://bitbucket.org/yt_analysis/yt/pull-requests/2415/_/diff#comment-24979863"
                }
            },
            "pullrequest": {
                "title": "Expand `~` and environment variables in the config file parameters",
                "type": "pullrequest",
                "links": {
                    "self": {
                        "href": "https://api.bitbucket.org/2.0/repositories/yt_analysis/yt/pullrequests/2415"
                    },
                    "html": {
                        "href": "https://bitbucket.org/yt_analysis/yt/pull-requests/2415"
                    }
                },
                "id": 2415
            },
            "content": {
                "raw": "I abstracted the following deleted block into the added method above.",
                "html": "<p>I abstracted the following deleted block into the added method above.</p>",
                "markup": "markdown"
            },
            "created_on": "2016-10-11T03:01:10.032072+00:00",
            "updated_on": "2016-10-11T03:01:10.037262+00:00",
            "inline": {
                "from": 103,
                "path": "yt/utilities/tests/test_config.py",
                "to": null
            },
            "id": 24979863
        },
        {
            "user": {
                "links": {
                    "self": {
                        "href": "https://api.bitbucket.org/2.0/users/qobilidop"
                    },
                    "html": {
                        "href": "https://bitbucket.org/qobilidop/"
                    },
                    "avatar": {
                        "href": "https://bitbucket.org/account/qobilidop/avatar/32/"
                    }
                },
                "type": "user",
                "display_name": "Bili Dong",
                "uuid": "{3b9943d1-f045-4354-af1c-35efa961d7cd}",
                "username": "qobilidop"
            },
            "type": "pullrequest_comment",
            "links": {
                "self": {
                    "href": "https://api.bitbucket.org/2.0/repositories/yt_analysis/yt/pullrequests/2415/comments/24979982"
                },
                "html": {
                    "href": "https://bitbucket.org/yt_analysis/yt/pull-requests/2415/_/diff#comment-24979982"
                }
            },
            "parent": {
                "links": {
                    "self": {
                        "href": "https://api.bitbucket.org/2.0/repositories/yt_analysis/yt/pullrequests/2415/comments/24975731"
                    },
                    "html": {
                        "href": "https://bitbucket.org/yt_analysis/yt/pull-requests/2415/_/diff#comment-24975731"
                    }
                },
                "id": 24975731
            },
            "pullrequest": {
                "title": "Expand `~` and environment variables in the config file parameters",
                "type": "pullrequest",
                "links": {
                    "self": {
                        "href": "https://api.bitbucket.org/2.0/repositories/yt_analysis/yt/pullrequests/2415"
                    },
                    "html": {
                        "href": "https://bitbucket.org/yt_analysis/yt/pull-requests/2415"
                    }
                },
                "id": 2415
            },
            "content": {
                "raw": "I spent sometime studying how the `configparser` module works and figured out a way to define a custom `configparser.Interpolation` class to preprocess all the parameters before the value is returned in the `get` method.",
                "html": "<p>I spent sometime studying how the <code>configparser</code> module works and figured out a way to define a custom <code>configparser.Interpolation</code> class to preprocess all the parameters before the value is returned in the <code>get</code> method.</p>",
                "markup": "markdown"
            },
            "created_on": "2016-10-11T03:08:40.247422+00:00",
            "updated_on": "2016-10-11T03:08:40.252784+00:00",
            "id": 24979982
        }
    ]
}