{
    "links": {
        "decline": {
            "href": "https://api.bitbucket.org/2.0/repositories/yt_analysis/yt/pullrequests/2175/decline"
        },
        "approve": {
            "href": "https://api.bitbucket.org/2.0/repositories/yt_analysis/yt/pullrequests/2175/approve"
        },
        "html": {
            "href": "https://bitbucket.org/yt_analysis/yt/pull-requests/2175"
        },
        "activity": {
            "href": "https://api.bitbucket.org/2.0/repositories/yt_analysis/yt/pullrequests/2175/activity"
        },
        "self": {
            "href": "https://api.bitbucket.org/2.0/repositories/yt_analysis/yt/pullrequests/2175"
        },
        "commits": {
            "href": "https://api.bitbucket.org/2.0/repositories/yt_analysis/yt/pullrequests/2175/commits"
        },
        "merge": {
            "href": "https://api.bitbucket.org/2.0/repositories/yt_analysis/yt/pullrequests/2175/merge"
        },
        "statuses": {
            "href": "https://api.bitbucket.org/2.0/repositories/yt_analysis/yt/pullrequests/2175/statuses"
        },
        "comments": {
            "href": "https://api.bitbucket.org/2.0/repositories/yt_analysis/yt/pullrequests/2175/comments"
        },
        "diff": {
            "href": "https://api.bitbucket.org/2.0/repositories/yt_analysis/yt/pullrequests/2175/diff"
        }
    },
    "task_count": 0,
    "source": {
        "repository": {
            "full_name": "ngoldbaum/yt",
            "uuid": "{cb18d7d9-ab77-4e80-81ed-8d32a945e0ef}",
            "type": "repository",
            "links": {
                "self": {
                    "href": "https://api.bitbucket.org/2.0/repositories/ngoldbaum/yt"
                },
                "html": {
                    "href": "https://bitbucket.org/ngoldbaum/yt"
                },
                "avatar": {
                    "href": "https://bitbucket.org/ngoldbaum/yt/avatar/32/"
                }
            },
            "name": "yt"
        },
        "commit": {
            "hash": "c568bda39a77",
            "links": {
                "self": {
                    "href": "https://api.bitbucket.org/2.0/repositories/ngoldbaum/yt/commit/c568bda39a77"
                }
            }
        },
        "branch": {
            "name": "yt"
        }
    },
    "closed_by": {
        "username": "jzuhone",
        "type": "user",
        "links": {
            "self": {
                "href": "https://api.bitbucket.org/2.0/users/jzuhone"
            },
            "html": {
                "href": "https://bitbucket.org/jzuhone/"
            },
            "avatar": {
                "href": "https://bitbucket.org/account/jzuhone/avatar/32/"
            }
        },
        "display_name": "John ZuHone",
        "uuid": "{0c51edfa-e317-432f-bbef-7401c6e2aa8a}"
    },
    "title": "silence deprecation warning from IPython",
    "id": 2175,
    "comment_count": 0,
    "created_on": "2016-05-15T16:34:46.172280+00:00",
    "merge_commit": {
        "hash": "cfc61bdb1b70",
        "links": {
            "self": {
                "href": "https://api.bitbucket.org/2.0/repositories/yt_analysis/yt/commit/cfc61bdb1b70"
            }
        }
    },
    "comments": [],
    "reason": "",
    "type": "pullrequest",
    "close_source_branch": false,
    "state": "MERGED",
    "description": "We're supposed to import the `Config` object from traitlets going forward.",
    "author": {
        "username": "ngoldbaum",
        "type": "user",
        "links": {
            "self": {
                "href": "https://api.bitbucket.org/2.0/users/ngoldbaum"
            },
            "html": {
                "href": "https://bitbucket.org/ngoldbaum/"
            },
            "avatar": {
                "href": "https://bitbucket.org/account/ngoldbaum/avatar/32/"
            }
        },
        "display_name": "Nathan Goldbaum",
        "uuid": "{5dcd72da-6420-4a6d-9571-e75dffcac587}"
    },
    "updated_on": "2016-05-18T18:12:29.000045+00:00",
    "destination": {
        "repository": {
            "full_name": "yt_analysis/yt",
            "uuid": "{b73cb37c-40f2-493a-aaa9-41bc8d8974cc}",
            "type": "repository",
            "links": {
                "self": {
                    "href": "https://api.bitbucket.org/2.0/repositories/yt_analysis/yt"
                },
                "html": {
                    "href": "https://bitbucket.org/yt_analysis/yt"
                },
                "avatar": {
                    "href": "https://bitbucket.org/yt_analysis/yt/avatar/32/"
                }
            },
            "name": "yt"
        },
        "commit": {
            "hash": "506d890f8554",
            "links": {
                "self": {
                    "href": "https://api.bitbucket.org/2.0/repositories/yt_analysis/yt/commit/506d890f8554"
                }
            }
        },
        "branch": {
            "name": "yt"
        }
    }
}