{
    "reason": "",
    "state": "MERGED",
    "updated_on": "2015-03-12T17:55:51.043687+00:00",
    "comment_count": 0,
    "description": "I was confused about whether hexahedral_connectivity expected the coordinates of the cell centers or cell corners/vertices. I added documentation to clarify.",
    "created_on": "2015-03-11T20:34:54.962489+00:00",
    "task_count": 0,
    "merge_commit": {
        "links": {
            "self": {
                "href": "https://api.bitbucket.org/2.0/repositories/yt_analysis/yt/commit/e99aa3a05af5"
            }
        },
        "hash": "e99aa3a05af5"
    },
    "title": "Added documentation to hexahedral mesh methods for clarity:",
    "links": {
        "diff": {
            "href": "https://api.bitbucket.org/2.0/repositories/yt_analysis/yt/pullrequests/1495/diff"
        },
        "decline": {
            "href": "https://api.bitbucket.org/2.0/repositories/yt_analysis/yt/pullrequests/1495/decline"
        },
        "self": {
            "href": "https://api.bitbucket.org/2.0/repositories/yt_analysis/yt/pullrequests/1495"
        },
        "activity": {
            "href": "https://api.bitbucket.org/2.0/repositories/yt_analysis/yt/pullrequests/1495/activity"
        },
        "merge": {
            "href": "https://api.bitbucket.org/2.0/repositories/yt_analysis/yt/pullrequests/1495/merge"
        },
        "commits": {
            "href": "https://api.bitbucket.org/2.0/repositories/yt_analysis/yt/pullrequests/1495/commits"
        },
        "statuses": {
            "href": "https://api.bitbucket.org/2.0/repositories/yt_analysis/yt/pullrequests/1495/statuses"
        },
        "approve": {
            "href": "https://api.bitbucket.org/2.0/repositories/yt_analysis/yt/pullrequests/1495/approve"
        },
        "html": {
            "href": "https://bitbucket.org/yt_analysis/yt/pull-requests/1495"
        },
        "comments": {
            "href": "https://api.bitbucket.org/2.0/repositories/yt_analysis/yt/pullrequests/1495/comments"
        }
    },
    "closed_by": {
        "links": {
            "self": {
                "href": "https://api.bitbucket.org/2.0/users/atmyers"
            },
            "html": {
                "href": "https://bitbucket.org/atmyers/"
            },
            "avatar": {
                "href": "https://bitbucket.org/account/atmyers/avatar/32/"
            }
        },
        "type": "user",
        "display_name": "Andrew Myers",
        "uuid": "{651c5647-b78f-4cd9-8d9a-5d6e8c9ac8d3}",
        "username": "atmyers"
    },
    "id": 1495,
    "type": "pullrequest",
    "author": {
        "links": {
            "self": {
                "href": "https://api.bitbucket.org/2.0/users/Yurlungur"
            },
            "html": {
                "href": "https://bitbucket.org/Yurlungur/"
            },
            "avatar": {
                "href": "https://bitbucket.org/account/Yurlungur/avatar/32/"
            }
        },
        "type": "user",
        "display_name": "Jonah Miller",
        "uuid": "{bec767b0-0d2d-4ff7-9b50-3ac98171078e}",
        "username": "Yurlungur"
    },
    "source": {
        "branch": {
            "name": "yt"
        },
        "commit": null,
        "repository": null
    },
    "close_source_branch": false,
    "destination": {
        "branch": {
            "name": "yt"
        },
        "commit": {
            "links": {
                "self": {
                    "href": "https://api.bitbucket.org/2.0/repositories/yt_analysis/yt/commit/569c909eee41"
                }
            },
            "hash": "569c909eee41"
        },
        "repository": {
            "full_name": "yt_analysis/yt",
            "type": "repository",
            "links": {
                "self": {
                    "href": "https://api.bitbucket.org/2.0/repositories/yt_analysis/yt"
                },
                "html": {
                    "href": "https://bitbucket.org/yt_analysis/yt"
                },
                "avatar": {
                    "href": "https://bitbucket.org/yt_analysis/yt/avatar/32/"
                }
            },
            "name": "yt",
            "uuid": "{b73cb37c-40f2-493a-aaa9-41bc8d8974cc}"
        }
    },
    "comments": []
}